{
  "instructions": [
    {
      "id": "STLVmFlowVar",
      "parameters": ["name", "max_value","min_value","step", "size","op"]
    },
    {
      "id": "STLVmWrFlowVar",
      "parameters": ["fv_name", "pkt_offset","offset_fixup","add_val","is_big"]
    },
    {
      "id": "STLVmFixIpv4",
      "parameters": ["offset"]
    },
    {
      "id": "STLVmFixChecksumHw",
      "parameters": ["l3_offset","l4_offset","l4_type"]
    }
  ],

  "instruction_params_meta": [
    {
      "id": "name",
      "name": "Name",
      "type": "STRING",
      "required": true,
      "defaultValue": "Not defined"
    },
    {
      "id": "init_value",
      "name": "Initial value",
      "type": "STRING",
      "defaultValue": "0"
    },
    {
      "id": "max_value",
      "name": "Maximum value",
      "type": "STRING",
      "required": true,
      "defaultValue": "0"
    },
    {
      "id": "min_value",
      "name": "Minimum value",
      "type": "STRING",
      "required": true,
      "defaultValue": "0"
    },
    {
      "id": "step",
      "name": "Step",
      "type": "NUMBER",
      "required": true,
      "defaultValue": "1"
    },
    {
      "id": "op",
      "name": "Operation",
      "type": "ENUM",
      "defaultValue": "inc",
      "dict": {
        "dec": "Decrement",
        "inc": "Increment",
        "random": "Random"
      },
      "required": true
    },
    {
      "id": "size",
      "name": "Size",
      "type": "ENUM",
      "defaultValue": "1",
      "dict": {
        "1": "1",
        "2": "2",
        "4": "4",
        "8": "8"
      }
    },
    {
      "id": "fv_name",
      "name": "Variable name",
      "type": "STRING",
      "required": true,
      "defaultValue": "Not Defined"
    },
    {
      "id": "pkt_offset",
      "name": "Offset",
      "type": "STRING",
      "required": true,
      "defaultValue": 0
    },
    {
      "id": "offset_fixup",
      "name": "offset_fixup",
      "type": "NUMBER",
      "defaultValue": 0
    },
    {
      "id": "add_val",
      "name": "add_val",
      "type": "NUMBER",
      "defaultValue": 0
    },
    {
      "id": "is_big",
      "name": "is_big",
      "type": "ENUM",
      "defaultValue": "true",
      "dict": {
        "true": "true",
        "false": "false"
      }
    },
    {
      "id": "offset",
      "name": "Offset",
      "type": "STRING",
      "required": true,
      "defaultValue": "Not defined"
    },
    {
      "id": "l3_offset",
      "name": "L3 offset",
      "type": "STRING",
      "required": true,
      "defaultValue": 0
    },
    {
      "id": "l4_offset",
      "name": "L4 offset",
      "type": "STRING",
      "required": true,
      "defaultValue": 0
    },
    {
      "id": "l4_type",
      "name": "L4 type",
      "type": "STRING",
      "required": true,
      "defaultValue": "Not defined"
    }
  ],
  "protocol_fields": {
    "IP": [
      "ttl",
      "src",
      "dst"
    ],
    "TCP": [
      "sport",
      "dport"
    ],
    "UDP": [
      "sport",
      "dport"
    ]
  },
  "global_params_meta":[
    {
      "id": "cache_size",
      "name": "Cache size",
      "type": "STRING",
      "defaultValue": "1000"
    }
  ]
}

